Metadata-Version: 2.1
Name: onavg_ind
Version: 0.0.5
Summary: Extension of neuroboros onavg pipeline to individual surfaces
Author-email: Ma Feilong <mafeilong@gmail.com>, Nikitas Koussis <nikitas.koussis@gmail.com>, Jayson Jeganathan <jayson.jeganathan@gmail.com>
License: MIT License
Project-URL: Homepage, https://github.com/nikitas-k/onavg-ind
Project-URL: Bug Tracker, https://github.com/nikitas-k/onavg-ind/issues
Classifier: Programming Language :: Python :: 3
Classifier: Programming Language :: Python :: 3 :: Only
Classifier: License :: OSI Approved :: MIT License
Classifier: Operating System :: OS Independent
Classifier: Intended Audience :: Science/Research
Classifier: Topic :: Scientific/Engineering
Requires-Python: >=3.6
License-File: LICENSE
Requires-Dist: numpy
Requires-Dist: scipy
Requires-Dist: nibabel
Requires-Dist: requests
Requires-Dist: joblib
Requires-Dist: pandas
Requires-Dist: Pillow
Requires-Dist: matplotlib
Requires-Dist: neuroboros
